getupandrun/__init__.py
getupandrun/cli/__init__.py
getupandrun/cli/bulk_commands.py
getupandrun/cli/commands.py
getupandrun/cli/main.py
getupandrun/cli/ui_command.py
getupandrun/cloud/__init__.py
getupandrun/cloud/detector.py
getupandrun/cloud/instructions.py
getupandrun/environment/__init__.py
getupandrun/environment/health.py
getupandrun/environment/manager.py
getupandrun/gpt/__init__.py
getupandrun/gpt/integration.py
getupandrun/kubernetes/__init__.py
getupandrun/kubernetes/generator.py
getupandrun/kubernetes/scripts.py
getupandrun/scaffold/__init__.py
getupandrun/scaffold/engine.py
getupandrun/scaffold/installers.py
getupandrun/scaffold/generators/__init__.py
getupandrun/scaffold/generators/backend.py
getupandrun/scaffold/generators/compose.py
getupandrun/scaffold/generators/database.py
getupandrun/scaffold/generators/dockerfile.py
getupandrun/scaffold/generators/frontend.py
getupandrun/templates/__init__.py
getupandrun/templates/definitions.py
getupandrun/templates/manager.py
getupandrun/ui/.env.example
getupandrun/ui/.gitignore
getupandrun/ui/.vercelignore
getupandrun/ui/DEPLOYMENT.md
getupandrun/ui/README.md
getupandrun/ui/eslint.config.mjs
getupandrun/ui/next-env.d.ts
getupandrun/ui/next.config.ts
getupandrun/ui/package.json
getupandrun/ui/postcss.config.mjs
getupandrun/ui/tsconfig.json
getupandrun/ui/vercel.json
getupandrun/ui/.vercel/README.txt
getupandrun/ui/.vercel/project.json
getupandrun/ui/app/favicon.ico
getupandrun/ui/app/globals.css
getupandrun/ui/app/layout.tsx
getupandrun/ui/app/page.tsx
getupandrun/ui/app/api/create/route.ts
getupandrun/ui/app/api/settings/route.ts
getupandrun/ui/app/api/templates/route.ts
getupandrun/ui/app/settings/page.tsx
getupandrun/ui/components/ProgressSpinner.tsx
getupandrun/ui/components/ProjectForm.tsx
getupandrun/ui/components/PromptInput.tsx
getupandrun/ui/components/TemplateCard.tsx
getupandrun/ui/components/TemplateGrid.tsx
getupandrun/ui/public/file.svg
getupandrun/ui/public/globe.svg
getupandrun-0.1.2.dist-info/METADATA
getupandrun-0.1.2.dist-info/WHEEL
getupandrun-0.1.2.dist-info/entry_points.txt
getupandrun-0.1.2.dist-info/top_level.txt
getupandrun-0.1.2.dist-info/RECORD
