Metadata-Version: 2.4
Name: getupandrun
Version: 0.1.2
Summary: A CLI tool that scaffolds development environments from natural language descriptions using GPT
Author-email: Nick Blaskovich <blaskocode19@gmail.com>
License: MIT
Project-URL: Homepage, https://github.com/your-org/getupandrun
Project-URL: Documentation, https://github.com/your-org/getupandrun#readme
Project-URL: Repository, https://github.com/your-org/getupandrun
Project-URL: Issues, https://github.com/your-org/getupandrun/issues
Keywords: cli,docker,scaffolding,gpt,development-environment,automation,devops
Classifier: Development Status :: 3 - Alpha
Classifier: Intended Audience :: Developers
Classifier: License :: OSI Approved :: MIT License
Classifier: Programming Language :: Python :: 3
Classifier: Programming Language :: Python :: 3.9
Classifier: Programming Language :: Python :: 3.10
Classifier: Programming Language :: Python :: 3.11
Classifier: Programming Language :: Python :: 3.12
Classifier: Topic :: Software Development :: Build Tools
Classifier: Topic :: Software Development :: Libraries :: Python Modules
Classifier: Topic :: System :: Systems Administration
Requires-Python: >=3.9
Requires-Dist: click>=8.1.0
Requires-Dist: rich>=13.0.0
Requires-Dist: openai>=1.0.0
Requires-Dist: docker>=6.0.0
Requires-Dist: pyyaml>=6.0
Requires-Dist: jinja2>=3.1.0
Requires-Dist: requests>=2.31.0
Provides-Extra: dev
Requires-Dist: pytest>=7.0.0; extra == "dev"
Requires-Dist: pytest-cov>=4.0.0; extra == "dev"
Requires-Dist: black>=23.0.0; extra == "dev"
Requires-Dist: flake8>=6.0.0; extra == "dev"
Requires-Dist: pylint>=2.17.0; extra == "dev"
Requires-Dist: mypy>=1.0.0; extra == "dev"
